Grigori-1.0.1.dist-info/METADATA
Grigori-1.0.1.dist-info/RECORD
Grigori-1.0.1.dist-info/WHEEL
Grigori-1.0.1.dist-info/top_level.txt
grigori/__init__.py
grigori/watcher.py
