Metadata-Version: 2.1
Name: Grigori
Version: 1.0.1
Summary: Watches a directory for file changes.
Home-page: https://github.com/stevenliebregt/grigori
Author: Steven Liebregt
Author-email: stevenliebregt@outlook.com
License: MIT
Platform: UNKNOWN
